http_request_aggregator/__init__.py
http_request_aggregator-0.4.dist-info/DESCRIPTION.rst
http_request_aggregator-0.4.dist-info/METADATA
http_request_aggregator-0.4.dist-info/RECORD
http_request_aggregator-0.4.dist-info/WHEEL
http_request_aggregator-0.4.dist-info/metadata.json
http_request_aggregator-0.4.dist-info/top_level.txt
